autopep8.py
autopep8-2.3.1.dist-info/AUTHORS.rst
autopep8-2.3.1.dist-info/LICENSE
autopep8-2.3.1.dist-info/METADATA
autopep8-2.3.1.dist-info/WHEEL
autopep8-2.3.1.dist-info/entry_points.txt
autopep8-2.3.1.dist-info/top_level.txt
autopep8-2.3.1.dist-info/RECORD
