Metadata-Version: 2.1
Name: autopep8
Version: 2.3.1
Summary: A tool that automatically formats Python code to conform to the PEP 8 style guide
Author-email: Hideo Hattori <hhatto.jp@gmail.com>
Project-URL: Repository, https://github.com/hhatto/autopep8
Keywords: automation,pep8,format,pycodestyle
Classifier: Development Status :: 5 - Production/Stable
Classifier: Environment :: Console
Classifier: Intended Audience :: Developers
Classifier: License :: OSI Approved :: MIT License
Classifier: Operating System :: OS Independent
Classifier: Programming Language :: Python
Classifier: Programming Language :: Python :: 3
Classifier: Programming Language :: Python :: 3.8
Classifier: Programming Language :: Python :: 3.9
Classifier: Programming Language :: Python :: 3.10
Classifier: Programming Language :: Python :: 3.11
Classifier: Programming Language :: Python :: 3.12
Classifier: Topic :: Software Development :: Libraries :: Python Modules
Classifier: Topic :: Software Development :: Quality Assurance
Requires-Python: >=3.8
License-File: LICENSE
License-File: AUTHORS.rst
Requires-Dist: pycodestyle>=2.12.0
Requires-Dist: tomli; python_version < "3.11"
